odoo/addons/rental_check_availability/README.rst
odoo/addons/rental_check_availability/__init__.py
odoo/addons/rental_check_availability/__manifest__.py
odoo/addons/rental_check_availability/README/CONTRIBUTORS.rst
odoo/addons/rental_check_availability/README/DESCRIPTION.rst
odoo/addons/rental_check_availability/README/HISTORY.rst
odoo/addons/rental_check_availability/README/USAGE.rst
odoo/addons/rental_check_availability/i18n/de.po
odoo/addons/rental_check_availability/i18n/rental_check_availability.pot
odoo/addons/rental_check_availability/models/__init__.py
odoo/addons/rental_check_availability/models/sale.py
odoo/addons/rental_check_availability/static/description/icon.png
odoo/addons/rental_check_availability/static/description/index.html
odoo/addons/rental_check_availability/tests/__init__.py
odoo/addons/rental_check_availability/tests/test_check_availability.py
odoo/addons/rental_check_availability/views/sale_view.xml
odoo12_addon_rental_check_availability-12.0.1.0.1.dist-info/METADATA
odoo12_addon_rental_check_availability-12.0.1.0.1.dist-info/WHEEL
odoo12_addon_rental_check_availability-12.0.1.0.1.dist-info/top_level.txt
odoo12_addon_rental_check_availability-12.0.1.0.1.dist-info/RECORD
