Metadata-Version: 2.1
Name: odoo12-addon-rental-check-availability
Version: 12.0.1.0.1
Summary: Extends the sale_rental module for checking availability of the rented product.
Home-page: https://github.com/OCA/vertical-rental
Author: Odoo Community Association (OCA), Elego Software Solutions GmbH
Author-email: support@odoo-community.org
License: AGPL-3
Platform: UNKNOWN
Classifier: Programming Language :: Python
Classifier: Framework :: Odoo
Classifier: Framework :: Odoo :: 12.0
Classifier: License :: OSI Approved :: GNU Affero General Public License v3
Requires-Python: >=3.5
Requires-Dist: odoo12-addon-rental-pricelist
Requires-Dist: odoo (<12.1dev,>=12.0a)
